nrstitcher_utils/__init__.py
nrstitcher_utils/version.py
nrstitcher_utils/app/__init__.py
nrstitcher_utils/app/nrs_clean_scories.py
nrstitcher_utils/app/nrs_config_id16a_ht.py
nrstitcher_utils/core/__init__.py
nrstitcher_utils/core/h5_settings.py
nrstitcher_utils/core/ht_vol.py
nrstitcher_utils/core/utils.py
nrstitcher_utils/resources/__init__.py
nrstitcher_utils/resources/config_files/__init__.py
nrstitcher_utils/resources/config_files/slurm_config_id16a.txt
nrstitcher_utils-1.1.2.dist-info/licenses/LICENSE
nrstitcher_utils-1.1.2.dist-info/METADATA
nrstitcher_utils-1.1.2.dist-info/WHEEL
nrstitcher_utils-1.1.2.dist-info/entry_points.txt
nrstitcher_utils-1.1.2.dist-info/top_level.txt
nrstitcher_utils-1.1.2.dist-info/RECORD
