Metadata-Version: 2.4
Name: nrstitcher_utils
Version: 1.1.2
Summary: NRStitcher utils for esrf usage
Author: Arttu Miettenen, Yervand Azatian
Author-email: Jayde Livingstone <jayde.livingstone@gmail.com>, Henri Payno <henri.payno@esrf.fr>
License: The nrstitcher_utils library goal is to ease usage of nrstitcher at esrf
Project-URL: Homepage, https://gitlab.esrf.fr/tomotools/nrstitcher_utils
Project-URL: Documentation, https://readthedocs.org/projects/nrstitcher_utils
Project-URL: Repository, https://gitlab.esrf.fr/tomotools/nrstitcher_utils
Project-URL: Changelog, https://gitlab.esrf.fr/tomotools/nrstitcher_utils/-/blob/main/CHANGELOG.md
Keywords: nrstitcher,pi2,tomography,tomotools,esrf
Classifier: Development Status :: 5 - Production/Stable
Classifier: Intended Audience :: Developers
Classifier: Intended Audience :: Science/Research
Classifier: Programming Language :: Python :: 3
Classifier: Programming Language :: Python :: 3.8
Classifier: Programming Language :: Python :: 3.9
Classifier: Programming Language :: Python :: 3.10
Classifier: Programming Language :: Python :: 3.11
Classifier: Programming Language :: Python :: 3.12
Classifier: Environment :: Console
Classifier: License :: OSI Approved :: MIT License
Classifier: Operating System :: Unix
Classifier: Operating System :: MacOS :: MacOS X
Classifier: Operating System :: POSIX
Classifier: Topic :: Scientific/Engineering :: Physics
Classifier: Topic :: Scientific/Engineering :: Medical Science Apps.
Requires-Python: >=3.8
License-File: LICENSE
Requires-Dist: packaging
Requires-Dist: h5py
Requires-Dist: tomoscan
Provides-Extra: test
Requires-Dist: pytest; extra == "test"
Provides-Extra: doc
Requires-Dist: Sphinx<5.2.0,>=4.0.0; extra == "doc"
Requires-Dist: nbsphinx; extra == "doc"
Requires-Dist: nbconvert; extra == "doc"
Requires-Dist: pandoc; extra == "doc"
Requires-Dist: sphinx_autodoc_typehints; extra == "doc"
Requires-Dist: pydata_sphinx_theme; extra == "doc"
Dynamic: license-file
